LICENSE
MANIFEST.in
README.rst
setup.py
django_report_diff.egg-info/PKG-INFO
django_report_diff.egg-info/SOURCES.txt
django_report_diff.egg-info/dependency_links.txt
django_report_diff.egg-info/requires.txt
django_report_diff.egg-info/top_level.txt
report_diff/__init__.py
report_diff/apps.py
report_diff/asgi.py
report_diff/settings.py
report_diff/urls.py
report_diff/wsgi.py
report_diff/bi_report/__init__.py
report_diff/bi_report/admin.py
report_diff/bi_report/apps.py
report_diff/bi_report/models.py
report_diff/bi_report/tests.py
report_diff/bi_report/urls.py
report_diff/bi_report/views.py
report_diff/bi_report/migrations/__init__.py